django_user_tasks-3.4.4.dist-info/licenses/AUTHORS
django_user_tasks-3.4.4.dist-info/licenses/LICENSE.txt
user_tasks/__init__.py
user_tasks/admin.py
user_tasks/apps.py
user_tasks/conf.py
user_tasks/exceptions.py
user_tasks/filters.py
user_tasks/models.py
user_tasks/rules.py
user_tasks/serializers.py
user_tasks/signals.py
user_tasks/tasks.py
user_tasks/urls.py
user_tasks/utils.py
user_tasks/views.py
user_tasks/migrations/0001_initial.py
user_tasks/migrations/0002_artifact_file_storage.py
user_tasks/migrations/0003_url_max_length.py
user_tasks/migrations/0004_url_textfield.py
user_tasks/migrations/0005_mariadb_uuid_conversion.py
user_tasks/migrations/__init__.py
django_user_tasks-3.4.4.dist-info/METADATA
django_user_tasks-3.4.4.dist-info/WHEEL
django_user_tasks-3.4.4.dist-info/top_level.txt
django_user_tasks-3.4.4.dist-info/RECORD
