Metadata-Version: 2.4
Name: django-user-tasks
Version: 3.4.4
Summary: Management of user-triggered asynchronous tasks in Django projects
Home-page: https://github.com/openedx/django-user-tasks
Author: edX
Author-email: oscm@edx.org
License: Apache Software License 2.0
Keywords: Django edx
Classifier: Development Status :: 4 - Beta
Classifier: Framework :: Django
Classifier: Framework :: Django :: 4.2
Classifier: Framework :: Django :: 5.2
Classifier: Intended Audience :: Developers
Classifier: License :: OSI Approved :: Apache Software License
Classifier: Natural Language :: English
Classifier: Programming Language :: Python :: 3
Classifier: Programming Language :: Python :: 3.11
Classifier: Programming Language :: Python :: 3.12
License-File: LICENSE.txt
License-File: AUTHORS
Requires-Dist: Django
Requires-Dist: celery<6.0
Requires-Dist: django-model-utils>=2.0
Requires-Dist: djangorestframework>=3.0.4
Requires-Dist: drf_yasg
Dynamic: author
Dynamic: author-email
Dynamic: classifier
Dynamic: description
Dynamic: description-content-type
Dynamic: home-page
Dynamic: keywords
Dynamic: license
Dynamic: license-file
Dynamic: requires-dist
Dynamic: summary
